{
  "id": "zRGgErI 34 jagadguru zrI~candrazEkhara bhAratI ArAdhanA",
  "jsonClass": "HinduCalendarEvent",
  "priority": "vyaapti",
  "shlokas": [
    "sadA''tmadhyAnanirataM viSayEbhyaH paraGmukham.\nnaumi zAstrESu niSNAtaM candrazEkharabhAratIm.."
  ],
  "tags": [
    "MahapurushaEvents",
    "SringeriAradhanaDays"
  ],
  "timing": {
    "angam_number": 30,
    "angam_type": "tithi",
    "jsonClass": "HinduCalendarEventTiming",
    "kaala": "aparaahna",
    "month_number": 6,
    "month_type": "lunar_month"
  }
}